LICENSE
MANIFEST.in
README.md
requirements.txt
setup.py
src/rentrylib/__init__.py
src/rentrylib/rentry.py
src/rentrylib.egg-info/PKG-INFO
src/rentrylib.egg-info/SOURCES.txt
src/rentrylib.egg-info/dependency_links.txt
src/rentrylib.egg-info/requires.txt
src/rentrylib.egg-info/top_level.txt