Metadata-Version: 2.1
Name: rentrylib
Version: 1.0.0
Summary: A python library for interfacing with the paste-site https://rentry.org
Home-page: https://github.com/yntha/rentrylib
Author: anthy
Author-email: bguznvjk@gmail.com
License: EPL-1.0
License-File: LICENSE
